aemo_to_tariff/__init__.py
aemo_to_tariff/ausgrid.py
aemo_to_tariff/ausnet.py
aemo_to_tariff/convert.py
aemo_to_tariff/endeavour.py
aemo_to_tariff/energex.py
aemo_to_tariff/ergon.py
aemo_to_tariff/essential.py
aemo_to_tariff/evoenergy.py
aemo_to_tariff/jemena.py
aemo_to_tariff/powercor.py
aemo_to_tariff/sapower.py
aemo_to_tariff/tasnetworks.py
aemo_to_tariff/united.py
aemo_to_tariff/victoria.py
aemo_to_tariff-0.7.12.dist-info/licenses/LICENSE
test/__init__.py
test/test_ausgrid.py
test/test_ausnet.py
test/test_convert.py
test/test_endeavour.py
test/test_energex.py
test/test_ergon.py
test/test_essential.py
test/test_evoenergy.py
test/test_jemena.py
test/test_sapower.py
test/test_tasnetworks.py
test/test_victoria.py
aemo_to_tariff-0.7.12.dist-info/METADATA
aemo_to_tariff-0.7.12.dist-info/WHEEL
aemo_to_tariff-0.7.12.dist-info/top_level.txt
aemo_to_tariff-0.7.12.dist-info/RECORD
