Metadata-Version: 2.4
Name: aemo_to_tariff
Version: 0.7.12
Summary: Convert spot prices from $/MWh to c/kWh for different networks and tariffs
Author: Ian Connor
Author-email: Ian Connor <ian@powston.com>
License: MIT
Project-URL: Homepage, https://github.com/powston/aemo_to_tariff
Project-URL: Repository, https://github.com/powston/aemo_to_tariff
Project-URL: Issues, https://github.com/powston/aemo_to_tariff/issues
Platform: UNKNOWN
Classifier: Programming Language :: Python :: 3.9
Classifier: Programming Language :: Python :: 3.10
Classifier: Programming Language :: Python :: 3.11
Classifier: License :: OSI Approved :: MIT License
Classifier: Operating System :: OS Independent
Requires-Python: >=3.9
License-File: LICENSE
Requires-Dist: pytz
Dynamic: author
Dynamic: license-file
Dynamic: requires-python
